django_dbq/__init__.py
django_dbq/models.py
django_dbq/tasks.py
django_dbq/tests.py
django_dbq/management/__init__.py
django_dbq/management/commands/__init__.py
django_dbq/management/commands/delete_old_jobs.py
django_dbq/management/commands/queue_depth.py
django_dbq/management/commands/worker.py
django_dbq/migrations/0001_initial.py
django_dbq/migrations/0002_auto_20151016_1027.py
django_dbq/migrations/0003_auto_20180713_1000.py
django_dbq/migrations/0004_auto_20210818_0247.py
django_dbq/migrations/0005_job_run_after.py
django_dbq/migrations/0006_alter_job_state.py
django_dbq/migrations/__init__.py
django_db_queue-3.3.0.dist-info/LICENSE
django_db_queue-3.3.0.dist-info/METADATA
django_db_queue-3.3.0.dist-info/WHEEL
django_db_queue-3.3.0.dist-info/top_level.txt
django_db_queue-3.3.0.dist-info/RECORD
