Metadata-Version: 2.1
Name: django-db-queue
Version: 3.3.0
Summary: Simple database-backed job queue system
Home-page: http://www.dabapps.com
Author: DabApps
Author-email: contact@dabapps.com
License: BSD
Platform: UNKNOWN
Requires-Python: >=3.9
Requires-Dist: Django>=4.2
